zeroae/cli/__init__.py
zeroae/cli/__main__.py
zeroae/cli/_version.py
zeroae/cli/cli.py
zeroae_cli-0.0.5.dist-info/LICENSE
zeroae_cli-0.0.5.dist-info/METADATA
zeroae_cli-0.0.5.dist-info/WHEEL
zeroae_cli-0.0.5.dist-info/entry_points.txt
zeroae_cli-0.0.5.dist-info/top_level.txt
zeroae_cli-0.0.5.dist-info/RECORD
