Metadata-Version: 2.1
Name: zeroae-cli
Version: 0.0.5
Summary: ZeroAE's CLI
Home-page: https://github.com/zeroae/zeroae-cli
Author: Patrick Sodré
Author-email: psodre@gmail.com
License: MIT
Keywords: cli zeroae
Platform: UNKNOWN
Classifier: Development Status :: 2 - Pre-Alpha
Classifier: Intended Audience :: Developers
Classifier: License :: OSI Approved :: MIT License
Classifier: Natural Language :: English
Classifier: Programming Language :: Python :: 3
Classifier: Programming Language :: Python :: 3.6
Classifier: Programming Language :: Python :: 3.7
Classifier: Programming Language :: Python :: 3.8
Requires-Python: >=3.6
Requires-Dist: click (>=7.0)
Requires-Dist: click-plugins
Requires-Dist: entrypoints
Provides-Extra: test
Requires-Dist: pytest (>=3) ; extra == 'test'
Requires-Dist: pytest-cov ; extra == 'test'
